moalpy/__init__.py
moalpy/optimizer.py
moalpy/multi_objectives/__init__.py
moalpy/multi_objectives/dominator.py
moalpy/multi_objectives/non_dominated_sorting.py
moalpy/multi_objectives/reference_direction.py
moalpy/swarm_based/MGO.py
moalpy/swarm_based/__init__.py
moalpy/utils/__init__.py
moalpy/utils/agent.py
moalpy/utils/history.py
moalpy/utils/logger.py
moalpy/utils/problem.py
moalpy/utils/space.py
moalpy/utils/target.py
moalpy/utils/transfer.py
moalpy/utils/validator.py
moalpy-0.0.4.dist-info/METADATA
moalpy-0.0.4.dist-info/WHEEL
moalpy-0.0.4.dist-info/top_level.txt
moalpy-0.0.4.dist-info/RECORD
