Metadata-Version: 2.2
Name: moalpy
Version: 0.0.4
Author: LDATuan
Requires-Dist: numpy>=1.26.4
Requires-Dist: scipy>=1.15.2
Requires-Dist: matplotlib>=3.8.4
Requires-Dist: pandas>=2.2.2
Dynamic: author
Dynamic: requires-dist
